{
    "@schema": "https://raw.githubusercontent.com/slicer/slicer/master/Modules/Loadable/Markups/Resources/Schema/markups-schema-v1.0.3.json#",
    "markups": [
        {
            "type": "ClosedCurve",
            "coordinateSystem": "LPS",
            "coordinateUnits": "mm",
            "locked": false,
            "fixedNumberOfControlPoints": false,
            "labelFormat": "%N-%d",
            "lastUsedControlPointNumber": 12,
            "controlPoints": [
                {
                    "id": "1",
                    "label": "n1_BasalRing-1",
                    "description": "",
                    "associatedNodeID": "vtkMRMLScalarVolumeNode1",
                    "position": [8.55, -146.96, -227.83],
                    "orientation": [-1.0, -0.0, -0.0, -0.0, -1.0, -0.0, 0.0, 0.0, 1.0],
                    "selected": true,
                    "locked": true,
                    "visibility": true,
                    "positionStatus": "defined"
                },
                {
                    "id": "2",
                    "label": "n1_BasalRing-2",
                    "description": "",
                    "associatedNodeID": "vtkMRMLScalarVolumeNode1",
                    "position": [14.05, -147.29, -223.89],
                    "orientation": [-1.0, -0.0, -0.0, -0.0, -1.0, -0.0, 0.0, 0.0, 1.0],
                    "selected": true,
                    "locked": true,
                    "visibility": true,
                    "positionStatus": "defined"
                },
                {
                    "id": "3",
                    "label": "n1_BasalRing-3",
                    "description": "",
                    "associatedNodeID": "vtkMRMLScalarVolumeNode1",
                    "position": [18.42, -148.96, -220.95],
                    "orientation": [-1.0, -0.0, -0.0, -0.0, -1.0, -0.0, 0.0, 0.0, 1.0],
                    "selected": true,
                    "locked": true,
                    "visibility": true,
                    "positionStatus": "defined"
                },
                {
                    "id": "4",
                    "label": "n1_BasalRing-4",
                    "description": "",
                    "associatedNodeID": "vtkMRMLScalarVolumeNode1",
                    "position": [20.91, -153.96, -219.82],
                    "orientation": [-1.0, -0.0, -0.0, -0.0, -1.0, -0.0, 0.0, 0.0, 1.0],
                    "selected": true,
                    "locked": true,
                    "visibility": true,
                    "positionStatus": "defined"
                },
                {
                    "id": "5",
                    "label": "n1_BasalRing-5",
                    "description": "",
                    "associatedNodeID": "vtkMRMLScalarVolumeNode1",
                    "position": [19.99, -160.44, -221.36],
                    "orientation": [-1.0, -0.0, -0.0, -0.0, -1.0, -0.0, 0.0, 0.0, 1.0],
                    "selected": true,
                    "locked": true,
                    "visibility": true,
                    "positionStatus": "defined"
                },
                {
                    "id": "6",
                    "label": "n1_BasalRing-6",
                    "description": "",
                    "associatedNodeID": "vtkMRMLScalarVolumeNode1",
                    "position": [15.63, -166.95, -225.4],
                    "orientation": [-1.0, -0.0, -0.0, -0.0, -1.0, -0.0, 0.0, 0.0, 1.0],
                    "selected": true,
                    "locked": true,
                    "visibility": true,
                    "positionStatus": "defined"
                },
                {
                    "id": "7",
                    "label": "n1_BasalRing-7",
                    "description": "",
                    "associatedNodeID": "vtkMRMLScalarVolumeNode1",
                    "position": [9.82, -168.54, -229.82],
                    "orientation": [-1.0, -0.0, -0.0, -0.0, -1.0, -0.0, 0.0, 0.0, 1.0],
                    "selected": true,
                    "locked": true,
                    "visibility": true,
                    "positionStatus": "defined"
                },
                {
                    "id": "8",
                    "label": "n1_BasalRing-8",
                    "description": "",
                    "associatedNodeID": "vtkMRMLScalarVolumeNode1",
                    "position": [4.65, -167.17, -233.39],
                    "orientation": [-1.0, -0.0, -0.0, -0.0, -1.0, -0.0, 0.0, 0.0, 1.0],
                    "selected": true,
                    "locked": true,
                    "visibility": true,
                    "positionStatus": "defined"
                },
                {
                    "id": "9",
                    "label": "n1_BasalRing-9",
                    "description": "",
                    "associatedNodeID": "vtkMRMLScalarVolumeNode1",
                    "position": [0.92, -163.52, -235.6],
                    "orientation": [-1.0, -0.0, -0.0, -0.0, -1.0, -0.0, 0.0, 0.0, 1.0],
                    "selected": true,
                    "locked": true,
                    "visibility": true,
                    "positionStatus": "defined"
                },
                {
                    "id": "10",
                    "label": "n1_BasalRing-10",
                    "description": "",
                    "associatedNodeID": "vtkMRMLScalarVolumeNode1",
                    "position": [-0.4, -158.94, -235.94],
                    "orientation": [-1.0, -0.0, -0.0, -0.0, -1.0, -0.0, 0.0, 0.0, 1.0],
                    "selected": true,
                    "locked": true,
                    "visibility": true,
                    "positionStatus": "defined"
                },
                {
                    "id": "11",
                    "label": "n1_BasalRing-11",
                    "description": "",
                    "associatedNodeID": "vtkMRMLScalarVolumeNode1",
                    "position": [-0.18, -153.22, -235.0],
                    "orientation": [-1.0, -0.0, -0.0, -0.0, -1.0, -0.0, 0.0, 0.0, 1.0],
                    "selected": true,
                    "locked": true,
                    "visibility": true,
                    "positionStatus": "defined"
                },
                {
                    "id": "12",
                    "label": "n1_BasalRing-12",
                    "description": "",
                    "associatedNodeID": "vtkMRMLScalarVolumeNode1",
                    "position": [3.54, -148.44, -231.66],
                    "orientation": [-1.0, -0.0, -0.0, -0.0, -1.0, -0.0, 0.0, 0.0, 1.0],
                    "selected": true,
                    "locked": true,
                    "visibility": true,
                    "positionStatus": "defined"
                }
            ],
            "measurements": [
                {
                    "name": "length",
                    "enabled": false,
                    "units": "mm",
                    "printFormat": "%-#4.4g%s"
                },
                {
                    "name": "curvature mean",
                    "enabled": false,
                    "printFormat": "%5.3f %s"
                },
                {
                    "name": "curvature max",
                    "enabled": false,
                    "printFormat": "%5.3f %s"
                },
                {
                    "name": "torsion mean",
                    "enabled": false,
                    "printFormat": "%5.3f %s"
                },
                {
                    "name": "torsion max",
                    "enabled": false,
                    "printFormat": "%5.3f %s"
                },
                {
                    "name": "area",
                    "enabled": false,
                    "units": "cm2",
                    "printFormat": "%-#4.4g%s"
                }
            ],
            "display": {
                "visibility": true,
                "opacity": 0.5,
                "color": [0.4, 1.0, 1.0],
                "selectedColor": [0.34509803921568627, 0.41568627450980394, 0.8431372549019608],
                "activeColor": [0.4, 1.0, 0.0],
                "propertiesLabelVisibility": true,
                "pointLabelsVisibility": false,
                "textScale": 3.0,
                "glyphType": "Sphere3D",
                "glyphScale": 2.0,
                "glyphSize": 5.0,
                "useGlyphScale": true,
                "sliceProjection": false,
                "sliceProjectionUseFiducialColor": true,
                "sliceProjectionOutlinedBehindSlicePlane": false,
                "sliceProjectionColor": [1.0, 1.0, 1.0],
                "sliceProjectionOpacity": 0.6,
                "lineThickness": 0.2,
                "lineColorFadingStart": 1.0,
                "lineColorFadingEnd": 10.0,
                "lineColorFadingSaturation": 1.0,
                "lineColorFadingHueOffset": 0.0,
                "handlesInteractive": false,
                "translationHandleVisibility": true,
                "rotationHandleVisibility": true,
                "scaleHandleVisibility": false,
                "interactionHandleScale": 3.0,
                "snapMode": "toVisibleSurface"
            }
        }
    ]
}